odoo8_addon_website_event_filter_organizer-8.0.1.0.0.99.dev10-py2.7-nspkg.pth
odoo8_addon_website_event_filter_organizer-8.0.1.0.0.99.dev10.dist-info/DESCRIPTION.rst
odoo8_addon_website_event_filter_organizer-8.0.1.0.0.99.dev10.dist-info/METADATA
odoo8_addon_website_event_filter_organizer-8.0.1.0.0.99.dev10.dist-info/RECORD
odoo8_addon_website_event_filter_organizer-8.0.1.0.0.99.dev10.dist-info/WHEEL
odoo8_addon_website_event_filter_organizer-8.0.1.0.0.99.dev10.dist-info/metadata.json
odoo8_addon_website_event_filter_organizer-8.0.1.0.0.99.dev10.dist-info/namespace_packages.txt
odoo8_addon_website_event_filter_organizer-8.0.1.0.0.99.dev10.dist-info/top_level.txt
odoo_addons/website_event_filter_organizer/README.rst
odoo_addons/website_event_filter_organizer/__init__.py
odoo_addons/website_event_filter_organizer/__openerp__.py
odoo_addons/website_event_filter_organizer/controllers/__init__.py
odoo_addons/website_event_filter_organizer/controllers/main.py
odoo_addons/website_event_filter_organizer/i18n/de.po
odoo_addons/website_event_filter_organizer/i18n/es.po
odoo_addons/website_event_filter_organizer/i18n/it.po
odoo_addons/website_event_filter_organizer/i18n/pt_BR.po
odoo_addons/website_event_filter_organizer/i18n/sl.po
odoo_addons/website_event_filter_organizer/i18n/website_event_filter_organizer.pot
odoo_addons/website_event_filter_organizer/static/description/icon.png
odoo_addons/website_event_filter_organizer/views/website_event.xml
